bus_interrogation_tunnel/__init__.py
bus_interrogation_tunnel/__main__.py
bus_interrogation_tunnel/bus.py
bus_interrogation_tunnel/util.py
bus_interrogation_tunnel-0.1.0.dist-info/entry_points.txt
bus_interrogation_tunnel-0.1.0.dist-info/WHEEL
bus_interrogation_tunnel-0.1.0.dist-info/METADATA
bus_interrogation_tunnel-0.1.0.dist-info/licenses/LICENSE
bus_interrogation_tunnel-0.1.0.dist-info/RECORD
