Metadata-Version: 2.1
Name: bus-interrogation-tunnel
Version: 0.1.0
Summary: BIT 班车查询接口（bitbus）
License: MIT
Author-email: Y.D.X. <73375426+YDX-2147483647@users.noreply.github.com>
Requires-Python: >=3.10
Classifier: Environment :: Console
Classifier: License :: OSI Approved :: MIT License
Classifier: Operating System :: OS Independent
Classifier: Programming Language :: Python :: 3
Classifier: Topic :: Home Automation
Classifier: Topic :: Utilities
Classifier: Typing :: Typed
Requires-Dist: requests>=2.28.2
Requires-Dist: rich>=13.3.2
Project-URL: Bug Tracker, https://github.com/YDX-2147483647/bus-interrogation-tunnel/issues
Project-URL: homepage, https://github.com/YDX-2147483647/bus-interrogation-tunnel
Project-URL: repository, https://github.com/YDX-2147483647/bus-interrogation-tunnel
